btecli/__init__.py
btecli/cli.py
btecli/lib/__init__.py
btecli/lib/cryptography/__init__.py
btecli/lib/cryptography/aes.py
btecli/lib/cryptography/wincred.py
btecli/lib/defaults/__init__.py
btecli/lib/dictutils/__init__.py
btecli/lib/formatting/__init__.py
btecli/lib/input/__init__.py
btecli/lib/input/streams.py
btecli/lib/logger/__init__.py
btecli/lib/options/__init__.py
btecli/lib/options/mexclusive.py
btecli/lib/plugin/__init__.py
btecli/lib/plugin/finder.py
btecli/lib/plugin/metadata.py
btecli/lib/plugin/plugins.py
btecli/lib/proc/__init__.py
btecli/lib/proc/local_invocation.py
btecli/lib/shell/__init__.py
btecli/lib/shell/bash_init.py
btecli/lib/shell/which.py
btecli-2.0.0.dist-info/METADATA
btecli-2.0.0.dist-info/WHEEL
btecli-2.0.0.dist-info/entry_points.txt
btecli-2.0.0.dist-info/top_level.txt
btecli-2.0.0.dist-info/RECORD
