Metadata-Version: 2.1
Name: btecli
Version: 2.0.0
Summary: Extensible CLI
Home-page: https://github.com/berttejeda/bert.ecli.git
Author: Engelbert Tejeda
Author-email: berttejeda@gmail.com
Keywords: bash,python,click,subprocess,yaml,cli,options,extensible,plugins,polyglot
Classifier: Development Status :: 3 - Alpha
Classifier: Intended Audience :: Developers
Classifier: Intended Audience :: Information Technology
Classifier: License :: OSI Approved :: MIT License
Classifier: Natural Language :: English
Classifier: Programming Language :: Python :: 2.7
Classifier: Programming Language :: Python :: 3
Classifier: Programming Language :: Python :: 3.4
Classifier: Programming Language :: Python :: 3.5
Classifier: Programming Language :: Python :: 3.6
Classifier: Programming Language :: Python :: 3.7
Classifier: Programming Language :: Python :: 3.10
Requires-Python: >=3.4
Requires-Dist: btconfig (<5.0.0,>=4.4.0)
Requires-Dist: bs4 (<0.1.0,>=0.0.1)
Requires-Dist: click (<9.0.0,>=8.1.3)
Requires-Dist: click-plugins (==1.1.1)
Requires-Dist: colorama (==0.4.3)
Requires-Dist: first (==2.0.2)
Requires-Dist: getversion (==1.0.2)
Requires-Dist: jello (==1.2.10)
Requires-Dist: lxml (==4.9.1)
Requires-Dist: pandas (<3.0.0,>=2.0.1)
Requires-Dist: PyCryptodome (<4.0.0,>=3.17)
Requires-Dist: PyYAML (<7.0.0,>=6.0)
Requires-Dist: requests (<2.30.0,>=2.28.1)
Requires-Dist: paramiko (<3.0.0,>=2.11.0) ; sys_platform == "win32" or sys_platform == "cygwin"
Provides-Extra: tests
Requires-Dist: pytest ; extra == 'tests'
Requires-Dist: pytest-cov ; extra == 'tests'
Requires-Dist: coveralls ; extra == 'tests'
Requires-Dist: flake8 ; extra == 'tests'
Requires-Dist: mypy ; extra == 'tests'
